{
  "url": "https://www.cmu.edu/health-services/about-us/news/open-enrollment.html",
  "title": "Open Enrollment and Immunization Requirements - \n                University Health Services -     Student Affairs - Carnegie Mellon University",
  "content": "Open Enrollment and Immunization Requirements\nImmunizations/TB Screening\nAll new fall semester students must submit immunization and Tuberculosis screening information by August 1st. Find more information about required immunizations\nhere\n.\nOpen Enrollment\nAll new Fall students and returning students must enroll or waive the student health insurance plan.\nStudent health insurance enrollments and waivers are accessible only during the Open Enrollment period in Student Information Online (SIO.)\nBetween July 1st to August 22nd: Log into SIO, select Campus Life, select Health Insurance and click the Highmark link to see your options to enroll in or waive the medical CMU SHIP.\nStudents who do not enroll or waive before the end of their open enrollment period will be enrolled in the student medical plan and incur an additional $50 fee.\nClick here for more information about open enrollment and student health insurance plans.",
  "extracted_info": {
    "phone_numbers": [],
    "emails": [],
    "hours": [],
    "addresses": [],
    "services": []
  },
  "category": "services",
  "timestamp": "2025-06-28T18:15:52.001229",
  "depth": 1
}